main.py
ASLMutetion-98.7.dist-info/METADATA
ASLMutetion-98.7.dist-info/WHEEL
ASLMutetion-98.7.dist-info/top_level.txt
ASLMutetion-98.7.dist-info/RECORD
